Workbook

Sheet 1. Ficha Técnica e Custos
A1: 🍰 FICHA TÉCNICA E CUSTO AUTOMÁTICO (250g)
A4: Ingrediente / Etapa | B4: Embalagem | C4: Preço Pago (R$) | D4: Uso na Receita | E4: Custo (R$) | G4: 💡 RESUMO FINAL POR POTINHO
A5: Farinha de Trigo | B5: 1000g | C5: 5.75 | D5: 360g | E5: =C5*(360/1000) | G5: Soma Custo Direto: | I5: =E11+E17+E18+E19
A6: Açúcar | B6: 1000g | C6: 4 | D6: 240g | E6: =C6*(240/1000) | G6: + Gás/Luz/Invisíveis (10%): | I6: =I5*0.1
A7: Margarina | B7: 250g | C7: 2.99 | D7: 100g | E7: =C7*(100/250) | G7: 🔥 CUSTO TOTAL: | I7: =I5+I6
A8: Leite Líquido | B8: 1000ml | C8: 7 | D8: 300ml | E8: =C8*(300/1000) | G8: Lucro Venda R$ 12,00: | I8: =12-I7
A9: Fermento em Pó | B9: 100g | C9: 3.75 | D9: 10g | E9: =C9*(10/100) | G9: Lucro Venda R$ 13,00: | I9: =13-I7
A10: Ovos | B10: 1 un | C10: 0.6 | D10: 3 un | E10: =C10*3
A11: 👉 CUSTO DA MASSA (POR BOLO) | D11: 1 un (1/21 da massa) | E11: =SUM(E5:E10)/21
A12: Leite Condensado (3 caixas) | B12: 395g | C12: 18.75 | D12: 3 caixas | E12: =C12
A13: Creme de Leite (3 caixas) | B13: 200g | C13: 9.75 | D13: 3 caixas | E13: =C13
A14: Chocolate em Pó 50% | B14: 1000g | C14: 55 | D14: 45g | E14: =C14*(45/1000)
A15: Coco Ralado | B15: 50g | C15: 3.99 | D15: 50g | E15: =C15
A16: Leite em Pó | B16: 200g | C16: 7.75 | D16: 30g | E16: =C16*(30/200)
A17: 👉 CUSTO DO RECHEIO (POR BOLO) | D17: 1 un (1/11 dos recheios) | E17: =SUM(E12:E16)/11
A18: Calda de Refrigerante | B18: Garrafa | C18: 12.5 | D18: Porção (~1/50) | E18: =C18/50
A19: Kit Embalagem + Delivery | B19: Kit | C19: 0.9 | D19: 1 kit | E19: =C19

Sheet 2. Controle de Vendas
A1: 📊 DIÁRIO DE VENDAS E REGISTRO DE PIX
A4: Data | B4: Cliente | C4: Local | D4: Qtd | E4: Preço (R$) | F4: Total (R$) | G4: Custo (R$) | H4: LUCRO LIMPO (R$)
A5: 14/07/2026 | B5: Andrea Rodrigues | C5: Casa | D5: 1 | E5: 12 | F5: =D5*E5 | G5: =D5*'1. Ficha Técnica e Custos'!$I$7 | H5: =F5-G5
A6: 14/07/2026 | B6: Maria Eduarda | C6: Casa | D6: 1 | E6: 12 | F6: =D6*E6 | G6: =D6*'1. Ficha Técnica e Custos'!$I$7 | H6: =F6-G6
A7: 15/07/2026 | B7: Marcus Wilker (Irmão) | C7: Trabalho | D7: 3 | E7: 13 | F7: =D7*E7 | G7: =D7*'1. Ficha Técnica e Custos'!$I$7 | H7: =F7-G7
A8: 16/07/2026 | B8: Kamilly Vitória | C8: Casa | D8: 1 | E8: 12 | F8: =D8*E8 | G8: =D8*'1. Ficha Técnica e Custos'!$I$7 | H8: =F8-G8
A9: 17/07/2026 | B9: Franklimilton | C9: Casa | D9: 1 | E9: 12 | F9: =D9*E9 | G9: =D9*'1. Ficha Técnica e Custos'!$I$7 | H9: =F9-G9
A10: 19/07/2026 | B10: Franklimilton | C10: Casa | D10: 2 | E10: 12 | F10: =D10*E10 | G10: =D10*'1. Ficha Técnica e Custos'!$I$7 | H10: =F10-G10
A11: 20/07/2026 | B11: Marcus Wilker (Irmão) | C11: Trabalho | D11: 4 | E11: 13 | F11: =D11*E11 | G11: =D11*'1. Ficha Técnica e Custos'!$I$7 | H11: =F11-G11
A12: 20/07/2026 | B12: Marcus Wilker (Irmão) | C12: Trabalho | D12: 5 | E12: 13 | F12: =D12*E12 | G12: =D12*'1. Ficha Técnica e Custos'!$I$7 | H12: =F12-G12
C13: TOTAL DO MÊS: | D13: =SUM(D5:D12) | F13: =SUM(F5:F12) | G13: =SUM(G5:G12) | H13: =SUM(H5:H12)

Sheet 3. Dashboard Visual
A1: 📈 DASHBOARD DE DESEMPENHO E GRÁFICOS
A4: Indicador | B4: Valor (R$) | C4: Descrição
A5: Faturamento Total de Vendas | B5: ='2. Controle de Vendas'!F13 | C5: Soma de todas as vendas do mês
A6: Custo Total de Produção Usado | B6: ='2. Controle de Vendas'!G13 | C6: Custo das matérias-primas e potes consumidos
A7: LUCRO LIMPO REAL | B7: ='2. Controle de Vendas'!H13 | C7: Dinheiro limpo no seu bolso!
